{
  "core": null,
  "plugins": [
    "https://github.com/wp-graphql/wp-graphql/releases/download/wp-graphql%2Fv2.16.0/wp-graphql.zip",
    "https://github.com/wpengine/wp-graphql-content-blocks/releases/download/v4.8.6/wp-graphql-content-blocks.zip",
    "https://downloads.wordpress.org/plugin/faustwp.latest-stable.zip",
    "./wordpress/plugins/kpf-core"
  ],
  "port": 8888,
  "testsEnvironment": false,
  "config": {
    "WP_DEBUG": true,
    "WP_DEBUG_LOG": true,
    "WP_DEBUG_DISPLAY": false,
    "SCRIPT_DEBUG": true
  },
  "lifecycleScripts": {
    "afterStart": "bash ./scripts/wp-bootstrap.sh"
  }
}
